shareql/__init__.py
shareql/__main__.py
shareql/ast/__init__.py
shareql/ast/boolop.py
shareql/ast/condition.py
shareql/ast/notop.py
shareql/ast/rule.py
shareql/ast/transformer.py
shareql/evaluate/RulesEvaluationResult.py
shareql/evaluate/__init__.py
shareql/evaluate/condition.py
shareql/evaluate/context.py
shareql/evaluate/evaluator.py
shareql/evaluate/results.py
shareql/examples/example_rules.txt
shareql/grammar/__init__.py
shareql/grammar/grammar.txt
shareql/grammar/parser.py
shareql/objects/__init__.py
shareql/objects/directory.py
shareql/objects/file.py
shareql/objects/host.py
shareql/objects/share.py
shareql/tests/run_tests.py
shareql/tests/test_can_explore.py
shareql/tests/test_default_rule.py
shareql/tests/test_depth.py
shareql/tests/test_empty_rules.py
shareql/tests/test_evaluate.py
shareql/tests/test_files.py
shareql/tests/test_parsing.py
shareql-1.0.0.dist-info/METADATA
shareql-1.0.0.dist-info/WHEEL
shareql-1.0.0.dist-info/entry_points.txt
shareql-1.0.0.dist-info/licenses/LICENSE
shareql-1.0.0.dist-info/RECORD
