Metadata-Version: 2.4
Name: shareql
Version: 1.0.0
Summary: A Python library and CLI for Share Query Language.
License: MIT
License-File: LICENSE
Author: p0dalirius
Requires-Python: >=3.11
Classifier: License :: OSI Approved :: MIT License
Classifier: Programming Language :: Python :: 3
Classifier: Programming Language :: Python :: 3.11
Classifier: Programming Language :: Python :: 3.12
Classifier: Programming Language :: Python :: 3.13
Classifier: Programming Language :: Python :: 3.14
Requires-Dist: lark
